r2lab_sidecar/__init__.py
r2lab_sidecar/__main__.py
r2lab_sidecar/server.py
r2lab_sidecar/version.py
r2lab_sidecar-0.11.0.dist-info/METADATA
r2lab_sidecar-0.11.0.dist-info/WHEEL
r2lab_sidecar-0.11.0.dist-info/entry_points.txt
r2lab_sidecar-0.11.0.dist-info/RECORD
