Metadata-Version: 2.4
Name: r2lab-sidecar
Version: 0.11.0
Summary: Testbed Management Companion for R2Lab
Project-URL: Homepage, https://github.com/r2lab.inria.fr
Author-email: Thierry Parmentelat <thierry.parmentelat@inria.fr>
License: CC-BY-NC-4.0
Keywords: R2lab,networking,testbed,wireless
Requires-Python: >=3.10
Requires-Dist: websockets
